{
  "session_id": "S0034",
  "started_at": "2026-03-05T14:00:00Z",
  "last_updated": "2026-03-05T14:15:00Z",
  "status": "completed",
  "focus": "PRD E2E Testing — Iteration 6 continued: Packages purchase/usage, loyalty points, error handling",
  "tasks_snapshot": {
    "total": 3,
    "not_started": 0,
    "in_progress": 0,
    "passing": 3,
    "failing": 0,
    "blocked": 0
  },
  "active_task_ids": [],
  "blockers": [],
  "notes": "S0034: Added 15 new E2E tests (245->260 total) across 3 updated files. New coverage: packages purchase/usage (6 tests), loyalty points/tiers (6 tests), error handling validation/network (3 tests). TypeScript clean, Vite build passes, 260 Playwright tests across 28 files. PRD progress: 217/272 (79%)."
}
